setup.py
src/lrung/LRUCache.py
src/lrung/__init__.py
src/lrung.egg-info/PKG-INFO
src/lrung.egg-info/SOURCES.txt
src/lrung.egg-info/dependency_links.txt
src/lrung.egg-info/top_level.txt